{"grid_size": 7, "cells": [[null, null, null, null, null, null, null], [null, "", null, "", "", "", null], [null, "", null, "", null, null, null], [null, "", "", "", "", null, null], [null, "", null, "", null, null, null], [null, null, null, null, null, null, null], [null, null, null, null, null, null, null]], "words": [{"id": 29, "word": "PACK", "definition": "捆扎；包装；打行李", "direction": "down", "start_row": 1, "start_col": 1, "length": 4, "clue_number": 1}, {"id": 649, "word": "BOW", "definition": "鞠躬；弯腰", "direction": "across", "start_row": 1, "start_col": 3, "length": 3, "clue_number": 2}, {"id": 963, "word": "BALD", "definition": "秃头的", "direction": "down", "start_row": 1, "start_col": 3, "length": 4, "clue_number": 2}, {"id": 567, "word": "COLA", "definition": "可乐饮料", "direction": "across", "start_row": 3, "start_col": 1, "length": 4, "clue_number": 3}], "prefilled": {"3-3": "L", "3-1": "C", "4-1": "K", "1-3": "B", "1-5": "W"}, "clue_numbers": [[null, null, null, null, null, null, null], [null, 1, null, 2, null, null, null], [null, null, null, null, null, null, null], [null, 3, null, null, null, null, null], [null, null, null, null, null, null, null], [null, null, null, null, null, null, null], [null, null, null, null, null, null, null]], "level": 13, "difficulty": "easy", "group": "senior4", "layout_type": "sparse", "group_name": "必修4", "prefill_ratio": 0.4}