{"grid_size": 10, "cells": [[null, null, null, null, null, null, null, null, null, null], [null, null, null, null, null, null, null, null, null, null], [null, "", "", "", "", null, "", null, null, null], [null, null, null, null, "", null, "", null, null, null], [null, null, null, null, "", null, "", null, null, null], [null, null, null, "", "", "", "", null, null, null], [null, null, null, "", null, null, null, null, null, null], [null, null, null, null, null, null, null, null, null, null], [null, null, null, null, null, null, null, null, null, null], [null, null, null, null, null, null, null, null, null, null]], "words": [{"id": 186, "word": "MEAN", "definition": "吝啬的；自私的；卑鄙的", "direction": "across", "start_row": 2, "start_col": 1, "length": 4, "clue_number": 1}, {"id": 777, "word": "NEST", "definition": "巢；窝", "direction": "down", "start_row": 2, "start_col": 4, "length": 4, "clue_number": 2}, {"id": 4, "word": "CALM", "definition": "（使）平静；（使）镇定", "direction": "down", "start_row": 2, "start_col": 6, "length": 4, "clue_number": 3}, {"id": 657, "word": "ATOM", "definition": "原子", "direction": "across", "start_row": 5, "start_col": 3, "length": 4, "clue_number": 4}, {"id": 54, "word": "AD", "definition": "公元", "direction": "down", "start_row": 5, "start_col": 3, "length": 2, "clue_number": 4}], "prefilled": {"5-4": "T", "5-3": "A", "5-6": "M", "4-6": "L", "2-4": "N", "2-2": "E"}, "clue_numbers": [[null, null, null, null, null, null, null, null, null, null], [null, null, null, null, null, null, null, null, null, null], [null, 1, null, null, 2, null, 3, null, null, null], [null, null, null, null, null, null, null, null, null, null], [null, null, null, null, null, null, null, null, null, null], [null, null, null, 4, null, null, null, null, null, null], [null, null, null, null, null, null, null, null, null, null], [null, null, null, null, null, null, null, null, null, null], [null, null, null, null, null, null, null, null, null, null], [null, null, null, null, null, null, null, null, null, null]], "level": 88, "difficulty": "easy", "group": "senior4", "layout_type": "sparse", "group_name": "必修4", "prefill_ratio": 0.4}