{"grid_size": 10, "cells": [[null, null, null, "", "", "", "", "", "", null], [null, null, "", null, null, null, null, null, "", null], [null, null, "", null, null, "", null, null, "", null], [null, null, "", null, null, "", null, null, "", null], [null, null, "", null, null, "", null, null, "", null], [null, null, "", "", "", "", "", null, "", null], [null, null, "", null, null, "", null, null, "", null], [null, null, null, null, "", "", "", "", "", ""], [null, null, null, null, null, null, null, null, null, null], [null, null, null, null, null, null, null, null, null, null]], "words": [{"id": 3882, "word": "E-MAIL", "definition": "n.(email)电子邮件", "direction": "across", "start_row": 0, "start_col": 3, "length": 6, "clue_number": 1, "alternatives": []}, {"id": 3250, "word": "LANGUAGE", "definition": "n. 语言； 措辞； 说法", "direction": "down", "start_row": 0, "start_col": 8, "length": 8, "clue_number": 2, "alternatives": [{"word": "LEMONADE", "definition": "n.柠檬水"}, {"word": "LAUSANNE", "definition": "洛桑（瑞士城市）"}, {"word": "LIBERATE", "definition": "v.解放；放出；释放"}, {"word": "LIFETIME", "definition": "n.一生；寿命；终生；使用期; adj.一生的；终身的"}, {"word": "LANDMINE", "definition": "n.地雷"}]}, {"id": 2838, "word": "CHOOSE", "definition": "v. [chose-chosen] 选择， 挑选", "direction": "down", "start_row": 1, "start_col": 2, "length": 6, "clue_number": 3, "alternatives": [{"word": "CHEESE", "definition": "奶酪"}, {"word": "PHRASE", "definition": "v. 用语言表达， 叙述; n.短语，词组，用语"}, {"word": "THIRST", "definition": "n. 渴， 口渴"}, {"word": "CHRIST", "definition": "n. 基督， 救世主"}, {"word": "THRUST", "definition": "vt.插；戳，刺; n. 戳， 刺； 要点， 要旨； 推力"}]}, {"id": 2787, "word": "DOLLAR", "definition": "n. 美元； 元", "direction": "down", "start_row": 2, "start_col": 5, "length": 6, "clue_number": 4, "alternatives": [{"word": "TALLER", "definition": "更高的"}, {"word": "COLLAR", "definition": "衣领"}, {"word": "TAILOR", "definition": "v. 定做; n.裁缝"}, {"word": "SAILOR", "definition": "n.水手，海员；乘船者"}, {"word": "ROLLER", "definition": "n.[机] 滚筒；[机] 滚轴；辊子；滚转机"}]}, {"id": 3076, "word": "STYLE", "definition": "n. 风格， 文体； 式样， 类型； 流行式样， 时尚", "direction": "across", "start_row": 5, "start_col": 2, "length": 5, "clue_number": 5, "alternatives": [{"word": "SMALL", "definition": "小的"}, {"word": "STILL", "definition": "仍然"}, {"word": "SHALL", "definition": "表示征求意见"}, {"word": "SMELL", "definition": "n.气味; v.闻出，闻到，嗅到"}, {"word": "SMILE", "definition": "v. 微笑， 露出笑容； 笑， 用微笑表示; n.微笑，笑容"}]}, {"id": 3700, "word": "DRAWER", "definition": "n.抽屉；开票人；出票人；起草者；酒馆侍", "direction": "across", "start_row": 7, "start_col": 4, "length": 6, "clue_number": 6, "alternatives": [{"word": "ERASER", "definition": "橡皮"}, {"word": "DRIVER", "definition": "司机"}, {"word": "TRAVEL", "definition": "旅行"}, {"word": "BROKEN", "definition": "破损的"}, {"word": "WRITER", "definition": "n. 作者， 作家"}]}], "prefilled": {"5-5": "L", "5-2": "S", "7-5": "R", "7-8": "E", "0-8": "L", "2-2": "H", "0-4": "-"}, "clue_numbers": [[null, null, null, 1, null, null, null, null, 2, null], [null, null, 3, null, null, null, null, null, null, null], [null, null, null, null, null, 4, null, null, null, null], [null, null, null, null, null, null, null, null, null, null], [null, null, null, null, null, null, null, null, null, null], [null, null, 5, null, null, null, null, null, null, null], [null, null, null, null, null, null, null, null, null, null], [null, null, null, null, 6, null, null, null, null, null], [null, null, null, null, null, null, null, null, null, null], [null, null, null, null, null, null, null, null, null, null]], "level": 113, "difficulty": "hard", "group": "junior", "layout_type": "sparse", "group_name": "初中词汇", "prefill_ratio": 0.15}