{"grid_size": 8, "cells": [[null, null, null, null, null, null, null, null], [null, null, null, null, null, "", null, null], [null, null, null, null, null, "", null, null], [null, null, null, "", null, "", null, null], [null, null, "", "", "", "", null, null], [null, null, null, "", null, null, null, null], ["", "", "", "", null, null, null, null], [null, null, null, null, null, null, null, null]], "words": [{"id": 1954, "word": "ROPE", "definition": "v. 用绳捆; n.绳索，线缆", "direction": "down", "start_row": 1, "start_col": 5, "length": 4, "clue_number": 1}, {"id": 3069, "word": "CASE", "definition": "n. 事例， 实例； 情况， 事实； 病例； 案件； 箱， 盒； 手提箱", "direction": "down", "start_row": 3, "start_col": 3, "length": 4, "clue_number": 2}, {"id": 2385, "word": "TALE", "definition": "n. 故事， 传说", "direction": "across", "start_row": 4, "start_col": 2, "length": 4, "clue_number": 3}, {"id": 2627, "word": "FIVE", "definition": "num. 五", "direction": "across", "start_row": 6, "start_col": 0, "length": 4, "clue_number": 4}], "prefilled": {"4-3": "A", "4-5": "E", "2-5": "O", "6-3": "E", "6-2": "V"}, "clue_numbers": [[null, null, null, null, null, null, null, null], [null, null, null, null, null, 1, null, null], [null, null, null, null, null, null, null, null], [null, null, null, 2, null, null, null, null], [null, null, 3, null, null, null, null, null], [null, null, null, null, null, null, null, null], [4, null, null, null, null, null, null, null], [null, null, null, null, null, null, null, null]], "level": 35, "difficulty": "easy", "group": "junior", "layout_type": "sparse", "group_name": "初中词汇", "prefill_ratio": 0.4}