{"grid_size": 6, "cells": [[null, null, null, null, null, null], [null, "", null, null, null, null], [null, "", null, null, "", null], ["", "", "", "", "", null], [null, "", null, null, "", null], [null, null, null, null, "", null]], "words": [{"id": 567, "word": "COLA", "definition": "可乐饮料", "direction": "down", "start_row": 1, "start_col": 1, "length": 4, "clue_number": 1}, {"id": 462, "word": "RELY", "definition": "依赖；依靠", "direction": "down", "start_row": 2, "start_col": 4, "length": 4, "clue_number": 2}, {"id": 891, "word": "SLIDE", "definition": "（使）滑动；（使）滑行", "direction": "across", "start_row": 3, "start_col": 0, "length": 5, "clue_number": 3}], "prefilled": {"3-4": "E", "3-1": "L", "2-1": "O", "5-4": "Y"}, "clue_numbers": [[null, null, null, null, null, null], [null, 1, null, null, null, null], [null, null, null, null, 2, null], [3, null, null, null, null, null], [null, null, null, null, null, null], [null, null, null, null, null, null]], "level": 6, "difficulty": "medium", "group": "senior5", "layout_type": "sparse", "group_name": "必修5", "prefill_ratio": 0.25}