{"grid_size": 8, "cells": [[null, "", "", "", "", "", "", ""], [null, null, null, null, null, null, null, ""], [null, "", "", "", "", "", "", ""], [null, null, null, null, "", null, null, ""], [null, "", "", "", "", "", null, ""], [null, null, null, null, "", null, null, ""], [null, "", "", "", "", "", "", null], [null, null, null, null, "", null, null, null]], "words": [{"id": 228, "word": "OUTSIDE", "definition": "在户外", "direction": "across", "start_row": 0, "start_col": 1, "length": 7, "clue_number": 1, "alternatives": [{"word": "MESSAGE", "definition": "n. 信息， 便条， 口信； 要点； 要旨"}, {"word": "PASSAGE", "definition": "n. 段落， 章节； 通道； 流逝， 推移"}, {"word": "SAUSAGE", "definition": "n. 香肠， 腊肠"}, {"word": "WEBSITE", "definition": "n.网站（全球资讯网的主机站）"}, {"word": "BEDSIDE", "definition": "n.床边；床头"}]}, {"id": 279, "word": "EIGHTY", "definition": "八十", "direction": "down", "start_row": 0, "start_col": 7, "length": 6, "clue_number": 2, "alternatives": [{"word": "ENGINE", "definition": "引擎"}, {"word": "EIGHTH", "definition": "num.第八; n. 八分之一"}, {"word": "ENGAGE", "definition": "vt. 使从事； 聘用； 吸引； 占用； 使订婚"}, {"word": "ENGULF", "definition": "v.吞没"}, {"word": "ENGIRD", "definition": "vt.使佩带, 围绕"}]}, {"id": 485, "word": "JUMPING", "definition": "跳", "direction": "across", "start_row": 2, "start_col": 1, "length": 7, "clue_number": 3, "alternatives": [{"word": "NIPPING", "definition": "adj.锋利的, 刺骨的, 讥刺的"}, {"word": "HELPING", "definition": "n.帮助, 协助, (食物)一份"}, {"word": "SLOPING", "definition": "adj. 倾斜的， 有坡度的"}]}, {"id": 2, "word": "PENCIL", "definition": "铅笔", "direction": "down", "start_row": 2, "start_col": 4, "length": 6, "clue_number": 4, "alternatives": [{"word": "PINKIE", "definition": "n.<口>小手指"}, {"word": "PUNDIT", "definition": "n.印度学者, 梵文学家, 博学者"}]}, {"id": 356, "word": "PLANT", "definition": "植物", "direction": "across", "start_row": 4, "start_col": 1, "length": 5, "clue_number": 5, "alternatives": [{"word": "PHONE", "definition": "电话"}, {"word": "PAINT", "definition": "绘画"}, {"word": "PLANE", "definition": "飞机"}, {"word": "POINT", "definition": "n. 要点； 观点； 点； 小数点； 时刻， 地点； 尖， 尖端； 分数， 得分"}, {"word": "POUND", "definition": "v. 强烈打击， 猛击； 心怦怦跳； 费力地移动; n.磅；英镑"}]}, {"id": 87, "word": "FAMILY", "definition": "家；家庭", "direction": "across", "start_row": 6, "start_col": 1, "length": 6, "clue_number": 6, "alternatives": [{"word": "EASILY", "definition": "容易地"}, {"word": "POLICY", "definition": "n.政策，方针；保险单"}, {"word": "SICILY", "definition": "西西里岛（意大利南部）"}, {"word": "FRUITY", "definition": "adj.果味的，（酒）有葡萄味的"}, {"word": "ENTITY", "definition": "n.独立存在体"}]}], "prefilled": {"4-4": "N", "4-1": "P", "6-4": "I", "6-6": "Y", "2-4": "P", "2-7": "G", "0-7": "E", "0-4": "S"}, "clue_numbers": [[null, 1, null, null, null, null, null, 2], [null, null, null, null, null, null, null, null], [null, 3, null, null, 4, null, null, null], [null, null, null, null, null, null, null, null], [null, 5, null, null, null, null, null, null], [null, null, null, null, null, null, null, null], [null, 6, null, null, null, null, null, null], [null, null, null, null, null, null, null, null]], "level": 91, "difficulty": "hard", "group": "grade6_1", "layout_type": "sparse", "group_name": "六年级上册", "prefill_ratio": 0.15}