{"grid_size": 9, "cells": [[null, null, null, "", "", "", "", "", ""], [null, null, null, null, null, "", null, null, ""], [null, null, null, null, null, "", null, null, ""], [null, null, null, "", null, "", null, null, ""], [null, null, "", "", "", "", "", null, ""], [null, null, null, "", null, "", null, null, ""], [null, null, null, "", null, null, null, null, null], [null, null, "", "", "", "", "", null, null], [null, null, null, null, null, null, null, null, null]], "words": [{"id": 44650, "word": "FORMAT", "definition": "n.开本, 版式, 形式, 格式", "direction": "across", "start_row": 0, "start_col": 3, "length": 6, "clue_number": 1}, {"id": 50075, "word": "REVISE", "definition": "v. 校订， 修正", "direction": "down", "start_row": 0, "start_col": 5, "length": 6, "clue_number": 2}, {"id": 46513, "word": "TRUISM", "definition": "n.真实性", "direction": "down", "start_row": 0, "start_col": 8, "length": 6, "clue_number": 3}, {"id": 43388, "word": "GAUZE", "definition": "n.薄纱, [医]纱布, 薄雾", "direction": "down", "start_row": 3, "start_col": 3, "length": 5, "clue_number": 4}, {"id": 45343, "word": "PATSY", "definition": "n.容易受骗的人, 懦夫", "direction": "across", "start_row": 4, "start_col": 2, "length": 5, "clue_number": 5}, {"id": 43369, "word": "FERRY", "definition": "n.摆渡, 渡船, 渡口", "direction": "across", "start_row": 7, "start_col": 2, "length": 5, "clue_number": 6}], "prefilled": {"4-5": "S", "4-3": "A", "0-5": "R", "7-3": "E", "0-8": "T", "7-5": "R", "3-8": "I"}, "clue_numbers": [[null, null, null, 1, null, 2, null, null, 3], [null, null, null, null, null, null, null, null, null], [null, null, null, null, null, null, null, null, null], [null, null, null, 4, null, null, null, null, null], [null, null, 5, null, null, null, null, null, null], [null, null, null, null, null, null, null, null, null], [null, null, null, null, null, null, null, null, null], [null, null, 6, null, null, null, null, null, null], [null, null, null, null, null, null, null, null, null]], "level": 72, "difficulty": "medium", "group": "gre", "layout_type": "sparse", "group_name": "GRE", "prefill_ratio": 0.25, "original_level": 72}