{"grid_size": 10, "cells": [[null, null, null, null, null, null, null, null, null, null], [null, null, null, null, null, null, null, null, null, null], [null, null, null, null, null, null, null, null, null, null], [null, null, null, null, null, null, null, null, null, null], [null, null, null, null, "", null, null, null, null, null], [null, null, null, "", "", "", "", null, null, null], [null, null, null, null, "", null, "", null, null, null], [null, null, "", "", "", null, "", null, null, null], [null, null, null, null, null, null, "", "", "", null], [null, null, null, null, null, null, null, null, null, null]], "words": [{"id": 474, "word": "LILY", "definition": "百合；百合花", "direction": "down", "start_row": 4, "start_col": 4, "length": 4, "clue_number": 1}, {"id": 598, "word": "SIGH", "definition": "叹息；叹气", "direction": "across", "start_row": 5, "start_col": 3, "length": 4, "clue_number": 2}, {"id": 428, "word": "HARM", "definition": "损害；危害", "direction": "down", "start_row": 5, "start_col": 6, "length": 4, "clue_number": 3}, {"id": 622, "word": "BAY", "definition": "海湾", "direction": "across", "start_row": 7, "start_col": 2, "length": 3, "clue_number": 4}, {"id": 736, "word": "MIX", "definition": "混合；调配", "direction": "across", "start_row": 8, "start_col": 6, "length": 3, "clue_number": 5}], "prefilled": {"5-4": "I", "5-6": "H", "7-4": "Y", "8-6": "M", "8-8": "X", "7-2": "B"}, "clue_numbers": [[null, null, null, null, null, null, null, null, null, null], [null, null, null, null, null, null, null, null, null, null], [null, null, null, null, null, null, null, null, null, null], [null, null, null, null, null, null, null, null, null, null], [null, null, null, null, 1, null, null, null, null, null], [null, null, null, 2, null, null, 3, null, null, null], [null, null, null, null, null, null, null, null, null, null], [null, null, 4, null, null, null, null, null, null, null], [null, null, null, null, null, null, 5, null, null, null], [null, null, null, null, null, null, null, null, null, null]], "level": 88, "difficulty": "easy", "group": "senior3", "layout_type": "sparse", "group_name": "必修3", "prefill_ratio": 0.4}