{"grid_size": 9, "cells": [[null, null, null, null, "", "", "", "", ""], [null, null, null, null, null, "", null, null, null], [null, null, null, null, "", "", "", "", ""], [null, null, null, null, "", null, null, null, null], [null, null, "", "", "", "", "", null, null], [null, null, null, null, "", null, null, null, null], [null, null, null, null, null, null, null, null, null], [null, null, null, null, null, null, null, null, null], [null, null, null, null, null, null, null, null, null]], "words": [{"id": 1132, "word": "CARRY", "definition": "携带；搬运；拿", "direction": "across", "start_row": 0, "start_col": 4, "length": 5, "clue_number": 1, "alternatives": [{"word": "MARRY", "definition": "v. 娶， 嫁， 和…结婚"}, {"word": "FAIRY", "definition": "n.仙子，小精灵"}, {"word": "MAORI", "definition": "adj.毛利人的"}, {"word": "DAIRY", "definition": "n.牛奶场；乳品公司"}, {"word": "HAIRY", "definition": "adj.毛发的，多毛的"}]}, {"id": 729, "word": "AGO", "definition": "以前", "direction": "down", "start_row": 0, "start_col": 5, "length": 3, "clue_number": 2, "alternatives": [{"word": "ADO", "definition": "n.纷扰, 忙乱"}]}, {"id": 450, "word": "SORRY", "definition": "抱歉的；；难过的；惋惜的", "direction": "across", "start_row": 2, "start_col": 4, "length": 5, "clue_number": 3, "alternatives": [{"word": "SOUND", "definition": "听起来好像"}, {"word": "SOLID", "definition": "adj.固体的；实心的；结实的，稳固的；可靠的；纯质的，纯色的; n. 固体"}, {"word": "SOLVE", "definition": "v. 解决， 处理； 解答"}, {"word": "SOUTH", "definition": "adv.向南方; adj. 南方的， 南部的， 来自南方的; n.南，南部"}, {"word": "SOCKS", "definition": "n.袜子（sock的复数）"}]}, {"id": 353, "word": "SWIM", "definition": "游泳", "direction": "down", "start_row": 2, "start_col": 4, "length": 4, "clue_number": 3, "alternatives": [{"word": "SHIP", "definition": "船"}, {"word": "SKIN", "definition": "n. 皮； 兽皮， 毛皮； 外皮， 外壳"}, {"word": "SUIT", "definition": "n. 一套衣服； 套"}, {"word": "SAIL", "definition": "v.航行；驾驶；在…上航行; n. 帆； 航行"}, {"word": "SKIP", "definition": "vi.  跳过； 跳读"}]}, {"id": 1196, "word": "QUICK", "definition": "快的，短时间的；迅速的", "direction": "across", "start_row": 4, "start_col": 2, "length": 5, "clue_number": 4, "alternatives": [{"word": "JUICE", "definition": "果汁"}, {"word": "QUIET", "definition": "安静的"}, {"word": "BUILD", "definition": "建造"}, {"word": "QUITE", "definition": "adv. 相当， 颇； 实际上， 真正地； 完全， 十分"}, {"word": "QUILT", "definition": "n.被子；床罩"}]}], "prefilled": {"4-4": "I", "4-3": "U", "2-4": "S", "2-5": "O", "0-5": "A", "0-7": "R"}, "clue_numbers": [[null, null, null, null, 1, 2, null, null, null], [null, null, null, null, null, null, null, null, null], [null, null, null, null, 3, null, null, null, null], [null, null, null, null, null, null, null, null, null], [null, null, 4, null, null, null, null, null, null], [null, null, null, null, null, null, null, null, null], [null, null, null, null, null, null, null, null, null], [null, null, null, null, null, null, null, null, null], [null, null, null, null, null, null, null, null, null]], "level": 67, "difficulty": "medium", "group": "junior8_2", "layout_type": "sparse", "group_name": "八年级下册", "prefill_ratio": 0.25}