{"grid_size": 10, "cells": [["", "", "", "", "", "", null, null, null, null], ["", null, "", null, null, null, null, null, null, null], ["", null, "", null, "", null, null, null, null, ""], ["", null, "", null, "", null, null, null, null, ""], ["", null, "", null, "", null, null, null, null, ""], ["", null, "", "", "", "", "", null, null, ""], ["", null, "", null, "", null, null, null, null, ""], ["", null, "", null, "", null, null, null, null, ""], ["", null, "", null, "", null, null, null, null, ""], [null, null, null, "", "", "", "", "", "", ""]], "words": [{"id": 32387, "word": "EMPIRE", "definition": "n.帝国", "direction": "across", "start_row": 0, "start_col": 0, "length": 6, "clue_number": 1, "alternatives": [{"word": "EXPECT", "definition": "期望"}, {"word": "EXPERT", "definition": "专家"}, {"word": "EXPORT", "definition": "vi. 出口; vt.输出; n. 出口"}, {"word": "EXPOSE", "definition": "vt. 暴露； 揭露"}, {"word": "EMPLOY", "definition": "vt. 雇用"}]}, {"id": 39015, "word": "ETHICALLY", "definition": "adv.伦理(学)上", "direction": "down", "start_row": 0, "start_col": 0, "length": 9, "clue_number": 1, "alternatives": [{"word": "EXHAUSTED", "definition": "adj.筋疲力尽的；疲惫不堪的"}, {"word": "EPHEMERAL", "definition": "adj.短暂的"}, {"word": "EXHIBITOR", "definition": "n.展出者,显示者"}, {"word": "ETHNOLOGY", "definition": "n. 民族学， 文化人类学"}]}, {"id": 36443, "word": "PRIESTESS", "definition": "n.女祭司, (基督教会以外的)神职人员", "direction": "down", "start_row": 0, "start_col": 2, "length": 9, "clue_number": 2, "alternatives": [{"word": "POLLUTION", "definition": "n. 污染"}, {"word": "POTENTIAL", "definition": "adj.潜在的，可能的; n. 潜力"}, {"word": "PRIMITIVE", "definition": "adj. 原始的， 远古的"}, {"word": "PRIVATELY", "definition": "adv.私下地"}, {"word": "PAKISTANI", "definition": "adj.巴基斯坦（人）的; n.巴基斯坦人"}]}, {"id": 31687, "word": "SQUIRREL", "definition": "n.松鼠", "direction": "down", "start_row": 2, "start_col": 4, "length": 8, "clue_number": 3, "alternatives": [{"word": "NATIONAL", "definition": "国家的"}, {"word": "OPTIONAL", "definition": "adj. 可选择的； 随意的"}, {"word": "OFFICIAL", "definition": "adj. 官方的， 政府的； 公务的; n.官员；高级职员"}, {"word": "MEDIEVAL", "definition": "adj.中古的，中世纪的"}, {"word": "HABITUAL", "definition": "adj.习惯性的，经常的"}]}, {"id": 36873, "word": "VALIDITY", "definition": "n.有效性, 合法性, 正确性", "direction": "down", "start_row": 2, "start_col": 9, "length": 8, "clue_number": 4, "alternatives": [{"word": "POLITELY", "definition": "adv.礼貌地；客气地"}, {"word": "MULTIPLY", "definition": "v.   相乘； 增加"}, {"word": "MILITARY", "definition": "adj.军事的，军用的"}, {"word": "DELIVERY", "definition": "n. 投递， 交付； 分娩； 讲话方式； 投递的邮件"}, {"word": "UNLIKELY", "definition": "adj.未必的，未必可能的"}]}, {"id": 39500, "word": "THIGH", "definition": "n.大腿, 股", "direction": "across", "start_row": 5, "start_col": 2, "length": 5, "clue_number": 5, "alternatives": [{"word": "THING", "definition": "事情"}, {"word": "THIRD", "definition": "第三"}, {"word": "THINK", "definition": "v.想，认为，以为"}, {"word": "TWICE", "definition": "adv. 两倍； 两次"}, {"word": "THICK", "definition": "adj. 厚的， 粗的； 笨的， 迟钝的； 稠的， 浓的； 密的， 密集的"}]}, {"id": 30808, "word": "ALREADY", "definition": "adv.已经", "direction": "across", "start_row": 9, "start_col": 3, "length": 7, "clue_number": 6, "alternatives": [{"word": "CLEARLY", "definition": "adv.清楚地；显然地"}, {"word": "CLARIFY", "definition": "v. 澄清， 阐明"}, {"word": "FLUENCY", "definition": "n. 流利， 流畅"}, {"word": "SLAVERY", "definition": "n.奴役；奴隶制度；奴隶身份"}, {"word": "BLUNTLY", "definition": "adv.坦率地，率直地"}]}], "prefilled": {"5-4": "I", "5-2": "T", "0-2": "P", "9-4": "L", "9-9": "Y", "4-9": "L", "0-0": "E", "2-0": "H"}, "clue_numbers": [[1, null, 2, null, null, null, null, null, null, null], [null, null, null, null, null, null, null, null, null, null], [null, null, null, null, 3, null, null, null, null, 4], [null, null, null, null, null, null, null, null, null, null], [null, null, null, null, null, null, null, null, null, null], [null, null, 5, null, null, null, null, null, null, null], [null, null, null, null, null, null, null, null, null, null], [null, null, null, null, null, null, null, null, null, null], [null, null, null, null, null, null, null, null, null, null], [null, null, null, 6, null, null, null, null, null, null]], "level": 487, "difficulty": "hard", "group": "toefl", "layout_type": "sparse", "group_name": "托福", "prefill_ratio": 0.15}