{"grid_size": 10, "cells": [[null, null, null, null, null, null, null, null, null, null], [null, "", "", "", "", "", "", null, null, null], [null, null, "", null, null, null, null, null, null, null], [null, null, "", null, null, "", null, null, "", null], [null, null, "", null, null, "", null, null, "", null], [null, null, "", "", "", "", "", null, "", null], [null, null, null, null, null, "", null, null, "", null], [null, null, null, "", "", "", "", "", "", null], [null, null, null, null, null, null, null, null, "", null], [null, null, null, null, null, "", "", "", "", ""]], "words": [{"id": 11974, "word": "PEPPER", "definition": "n.胡椒，胡椒粉; vt. 在…上撒； 使布满", "direction": "across", "start_row": 1, "start_col": 1, "length": 6, "clue_number": 1}, {"id": 14009, "word": "EXACT", "definition": "adj.确切的，精确的; vt. 强求， 索取", "direction": "down", "start_row": 1, "start_col": 2, "length": 5, "clue_number": 2}, {"id": 15225, "word": "BEGIN", "definition": "v.开始", "direction": "down", "start_row": 3, "start_col": 5, "length": 5, "clue_number": 3}, {"id": 12736, "word": "UNDERGO", "definition": "vt. 经历， 经受， 忍受； 接受", "direction": "down", "start_row": 3, "start_col": 8, "length": 7, "clue_number": 4}, {"id": 13034, "word": "TOUGH", "definition": "adj. 困难的， 难对付的； 坚强的， 能吃苦耐劳的； 健壮的； 坚硬的， 严格的； 老的， 硬的； 粗暴的， 充满暴力的", "direction": "across", "start_row": 5, "start_col": 2, "length": 5, "clue_number": 5}, {"id": 15099, "word": "FINGER", "definition": "n.手指；指状物", "direction": "across", "start_row": 7, "start_col": 3, "length": 6, "clue_number": 6}, {"id": 12250, "word": "PRIOR", "definition": "adj. 在前的； 优先的", "direction": "across", "start_row": 9, "start_col": 5, "length": 5, "clue_number": 7}], "prefilled": {"5-2": "T", "5-5": "G", "1-2": "E", "7-5": "N", "1-5": "E", "7-8": "R", "9-8": "O", "9-5": "P"}, "clue_numbers": [[null, null, null, null, null, null, null, null, null, null], [null, 1, 2, null, null, null, null, null, null, null], [null, null, null, null, null, null, null, null, null, null], [null, null, null, null, null, 3, null, null, 4, null], [null, null, null, null, null, null, null, null, null, null], [null, null, 5, null, null, null, null, null, null, null], [null, null, null, null, null, null, null, null, null, null], [null, null, null, 6, null, null, null, null, null, null], [null, null, null, null, null, null, null, null, null, null], [null, null, null, null, null, 7, null, null, null, null]], "level": 676, "difficulty": "hard", "group": "cet4", "layout_type": "sparse", "group_name": "大学四级", "prefill_ratio": 0.15, "original_level": 676}