{"grid_size": 10, "cells": [[null, null, null, null, null, null, null, null, null, null], [null, null, "", "", "", "", "", "", null, null], [null, null, null, null, null, "", null, null, null, null], [null, null, null, "", null, "", null, null, null, null], [null, null, null, "", null, "", null, null, null, null], [null, null, "", "", "", "", "", null, null, null], [null, null, null, "", null, "", null, null, null, null], [null, null, null, "", null, "", null, null, null, null], [null, null, "", "", "", "", "", "", null, null], [null, null, null, null, null, null, null, null, null, null]], "words": [{"id": 26932, "word": "CRADLE", "definition": "n.摇篮，策源地；支船架vt把放在摇篮里", "direction": "across", "start_row": 1, "start_col": 2, "length": 6, "clue_number": 1}, {"id": 29888, "word": "DOWNSIZE", "definition": "v. 缩小， 紧缩", "direction": "down", "start_row": 1, "start_col": 5, "length": 8, "clue_number": 2}, {"id": 25723, "word": "WARDEN", "definition": "n.管理员，监护人", "direction": "down", "start_row": 3, "start_col": 3, "length": 6, "clue_number": 3}, {"id": 27969, "word": "CRISP", "definition": "adj.脆的；干脆的; n.油炸马铃薯片; v.(使)发脆", "direction": "across", "start_row": 5, "start_col": 2, "length": 5, "clue_number": 4}, {"id": 27765, "word": "INTENT", "definition": "adj.(目光)不能移的，集中的，专心的，坚决的", "direction": "across", "start_row": 8, "start_col": 2, "length": 6, "clue_number": 5}], "prefilled": {"5-5": "S", "5-3": "R", "8-5": "E", "8-3": "N", "1-5": "D", "1-2": "C"}, "clue_numbers": [[null, null, null, null, null, null, null, null, null, null], [null, null, 1, null, null, 2, null, null, null, null], [null, null, null, null, null, null, null, null, null, null], [null, null, null, 3, null, null, null, null, null, null], [null, null, null, null, null, null, null, null, null, null], [null, null, 4, null, null, null, null, null, null, null], [null, null, null, null, null, null, null, null, null, null], [null, null, null, null, null, null, null, null, null, null], [null, null, 5, null, null, null, null, null, null, null], [null, null, null, null, null, null, null, null, null, null]], "level": 149, "difficulty": "hard", "group": "ielts", "layout_type": "sparse", "group_name": "雅思", "prefill_ratio": 0.15}