{"grid_size": 8, "cells": [[null, null, null, null, null, null, null, null], ["", "", "", "", "", "", null, ""], [null, null, null, null, "", null, null, ""], [null, null, "", null, "", null, null, ""], [null, "", "", "", "", "", null, ""], [null, null, "", null, "", null, null, ""], [null, null, "", null, null, null, null, ""], [null, "", "", "", "", "", "", ""]], "words": [{"id": 129, "word": "TWENTY", "definition": "二十", "direction": "across", "start_row": 1, "start_col": 0, "length": 6, "clue_number": 1}, {"id": 54, "word": "THREE", "definition": "三", "direction": "down", "start_row": 1, "start_col": 4, "length": 5, "clue_number": 2}, {"id": 160, "word": "GLASSES", "definition": "眼镜", "direction": "down", "start_row": 1, "start_col": 7, "length": 7, "clue_number": 3}, {"id": 41, "word": "PANDA", "definition": "大熊猫", "direction": "down", "start_row": 3, "start_col": 2, "length": 5, "clue_number": 4}, {"id": 48, "word": "WATER", "definition": "水", "direction": "across", "start_row": 4, "start_col": 1, "length": 5, "clue_number": 5}, {"id": 191, "word": "PARENTS", "definition": "父母", "direction": "across", "start_row": 7, "start_col": 1, "length": 7, "clue_number": 6}], "prefilled": {"4-2": "A", "4-4": "E", "1-4": "T", "1-0": "T", "7-2": "A", "7-7": "S", "1-7": "G"}, "clue_numbers": [[null, null, null, null, null, null, null, null], [1, null, null, null, 2, null, null, 3], [null, null, null, null, null, null, null, null], [null, null, 4, null, null, null, null, null], [null, 5, null, null, null, null, null, null], [null, null, null, null, null, null, null, null], [null, null, null, null, null, null, null, null], [null, 6, null, null, null, null, null, null]], "level": 81, "difficulty": "hard", "group": "grade4_1", "layout_type": "sparse", "group_name": "四年级上册", "prefill_ratio": 0.15}