{"grid_size": 10, "cells": [[null, null, null, null, null, "", "", "", "", ""], [null, null, "", null, null, "", null, null, null, null], [null, null, "", null, null, "", null, null, null, null], [null, null, "", null, "", "", "", "", "", null], [null, null, "", null, null, "", null, null, null, null], [null, null, "", "", "", "", "", null, null, null], [null, null, "", null, null, "", null, null, null, null], [null, null, "", "", "", "", "", "", null, null], [null, null, null, null, null, null, null, null, null, null], [null, null, null, null, null, null, null, null, null, null]], "words": [{"id": 7784, "word": "SPAIN", "definition": "n.西班牙", "direction": "across", "start_row": 0, "start_col": 5, "length": 5, "clue_number": 1}, {"id": 8937, "word": "STRORAGE", "definition": "n.贮藏，存储，储藏室", "direction": "down", "start_row": 0, "start_col": 5, "length": 8, "clue_number": 1}, {"id": 5025, "word": "CHAPTER", "definition": "n. 章", "direction": "down", "start_row": 1, "start_col": 2, "length": 7, "clue_number": 2}, {"id": 5089, "word": "TOAST", "definition": "vt.向…敬酒；烘，烤; n. 烤面包， 吐司； 祝酒， 祝酒词", "direction": "across", "start_row": 3, "start_col": 4, "length": 5, "clue_number": 3}, {"id": 7665, "word": "TODAY", "definition": "adv.今天；现今; n.今天；现今", "direction": "across", "start_row": 5, "start_col": 2, "length": 5, "clue_number": 4}, {"id": 6171, "word": "RETELL", "definition": "vt. 重讲， 重复， 复述", "direction": "across", "start_row": 7, "start_col": 2, "length": 6, "clue_number": 5}], "prefilled": {"5-2": "T", "5-5": "A", "7-5": "E", "7-2": "R", "0-5": "S", "0-7": "A", "3-5": "O", "3-7": "S"}, "clue_numbers": [[null, null, null, null, null, 1, null, null, null, null], [null, null, 2, null, null, null, null, null, null, null], [null, null, null, null, null, null, null, null, null, null], [null, null, null, null, 3, null, null, null, null, null], [null, null, null, null, null, null, null, null, null, null], [null, null, 4, null, null, null, null, null, null, null], [null, null, null, null, null, null, null, null, null, null], [null, null, 5, null, null, null, null, null, null, null], [null, null, null, null, null, null, null, null, null, null], [null, null, null, null, null, null, null, null, null, null]], "level": 786, "difficulty": "hard", "group": "senior", "layout_type": "sparse", "group_name": "高中词汇", "prefill_ratio": 0.15, "original_level": 786}