{"grid_size": 10, "cells": [[null, "L", null, null, "Y", null, null, null, null, ""], [null, "", null, null, "", null, null, null, null, "A"], [null, "", null, null, "", null, null, null, null, ""], ["", "I", "T", "", "R", "", "", "U", "", "E"], [null, "T", null, null, "S", null, null, null, null, ""], ["F", "A", "", "", "E", "", "", "", "I", "T"], [null, "", null, null, "L", null, null, null, null, "H"], [null, "", null, null, "", null, null, null, null, ""], [null, "", null, null, "", null, null, null, null, ""], [null, "N", null, null, "", null, null, null, null, "D"]], "revealed": [[false, true, false, false, true, false, false, false, false, false], [false, false, false, false, false, false, false, false, false, true], [false, false, false, false, false, false, false, false, false, false], [false, true, true, false, true, false, false, true, false, true], [false, true, false, false, true, false, false, false, false, false], [true, true, false, false, true, false, false, false, true, true], [false, false, false, false, true, false, false, false, false, true], [false, false, false, false, false, false, false, false, false, false], [false, false, false, false, false, false, false, false, false, false], [false, true, false, false, false, false, false, false, false, true]], "words": [{"id": 9011, "word": "LIMITATION", "definition": "n.限制，局限性", "direction": "down", "start_row": 0, "start_col": 1, "length": 10, "clue_number": 1}, {"id": 8505, "word": "YOURSELVES", "definition": "pron.你们自己；你们本人（yourself的复数）", "direction": "down", "start_row": 0, "start_col": 4, "length": 10, "clue_number": 2}, {"id": 10696, "word": "PARENTHOOD", "definition": "n.父母身份", "direction": "down", "start_row": 0, "start_col": 9, "length": 10, "clue_number": 3}, {"id": 6908, "word": "LITERATURE", "definition": "n. 文学", "direction": "across", "start_row": 3, "start_col": 0, "length": 10, "clue_number": 4}, {"id": 9890, "word": "FAHRENHEIT", "definition": "adj.华氏的; n.华氏温度", "direction": "across", "start_row": 5, "start_col": 0, "length": 10, "clue_number": 5}], "prefilled": {}, "clue_numbers": [[null, 1, null, null, 2, null, null, null, null, 3], [null, null, null, null, null, null, null, null, null, null], [null, null, null, null, null, null, null, null, null, null], [4, null, null, null, null, null, null, null, null, null], [null, null, null, null, null, null, null, null, null, null], [5, null, null, null, null, null, null, null, null, null], [null, null, null, null, null, null, null, null, null, null], [null, null, null, null, null, null, null, null, null, null], [null, null, null, null, null, null, null, null, null, null], [null, null, null, null, null, null, null, null, null, null]], "puzzle_type": "template", "density": 0.44, "level": 815, "difficulty": "hard", "group": "senior", "cross_validated": true, "layout_type": "dense", "group_name": "高中词汇", "prefill_ratio": 0.15}