{"grid_size": 10, "cells": [[null, null, null, "", null, null, null, null, null, null], ["", "N", "", "E", "F", "", "N", "I", "", ""], [null, null, null, "F", null, null, null, null, null, null], ["I", "", "L", "I", "", "E", "", "", "", "E"], [null, null, null, "", null, null, null, null, null, null], ["I", "", "S", "I", "", "T", "", "", "C", ""], [null, null, null, "", null, null, null, null, null, null], [null, null, null, "", null, null, null, null, null, null], [null, null, null, "", null, null, null, null, null, null], ["", "N", "", "E", "R", "T", "", "", "N", ""]], "revealed": [[false, false, false, false, false, false, false, false, false, false], [false, true, false, true, true, false, true, true, false, false], [false, false, false, true, false, false, false, false, false, false], [true, false, true, true, false, true, false, false, false, true], [false, false, false, false, false, false, false, false, false, false], [true, false, true, true, false, true, false, false, true, false], [false, false, false, false, false, false, false, false, false, false], [false, false, false, false, false, false, false, false, false, false], [false, false, false, false, false, false, false, false, false, false], [false, true, false, true, true, true, false, false, true, false]], "words": [{"id": 36318, "word": "DEFINITIVE", "definition": "adj.最后的,确定的", "direction": "down", "start_row": 0, "start_col": 3, "length": 10, "clue_number": 1}, {"id": 35624, "word": "INDEFINITE", "definition": "adj.不明确的，含糊的", "direction": "across", "start_row": 1, "start_col": 0, "length": 10, "clue_number": 2}, {"id": 37546, "word": "ILLITERATE", "definition": "n.文盲 a不识字的", "direction": "across", "start_row": 3, "start_col": 0, "length": 10, "clue_number": 3}, {"id": 36968, "word": "INSISTENCE", "definition": "n.坚持, 坚决主张", "direction": "across", "start_row": 5, "start_col": 0, "length": 10, "clue_number": 4}, {"id": 37594, "word": "INTERTWINE", "definition": "v.(使)纠缠,(使)缠绕", "direction": "across", "start_row": 9, "start_col": 0, "length": 10, "clue_number": 5}], "prefilled": {}, "clue_numbers": [[null, null, null, 1, null, null, null, null, null, null], [2, null, null, null, null, null, null, null, null, null], [null, null, null, null, null, null, null, null, null, null], [3, null, null, null, null, null, null, null, null, null], [null, null, null, null, null, null, null, null, null, null], [4, null, null, null, null, null, null, null, null, null], [null, null, null, null, null, null, null, null, null, null], [null, null, null, null, null, null, null, null, null, null], [null, null, null, null, null, null, null, null, null, null], [5, null, null, null, null, null, null, null, null, null]], "puzzle_type": "template", "density": 0.46, "level": 1326, "difficulty": "hard", "group": "toefl", "cross_validated": true, "layout_type": "dense", "group_name": "托福", "prefill_ratio": 0.15}