{"grid_size": 10, "cells": [[null, null, null, null, null, null, "", null, null, null], [null, null, null, null, null, null, "", null, null, null], [null, null, "", "", "", "", "", null, "", null], [null, null, null, null, null, null, "", "", "", ""], [null, null, null, null, "", null, "", null, "", null], [null, null, "", "", "", "", "", null, "", null], [null, null, null, null, "", null, null, null, null, null], [null, null, null, "", "", "", "", null, null, null], [null, null, null, null, "", null, null, null, null, null], [null, null, "", "", "", "", "", "", null, null]], "words": [{"id": 35804, "word": "SUNSET", "definition": "n.日落, 晚年", "direction": "down", "start_row": 0, "start_col": 6, "length": 6, "clue_number": 1, "alternatives": []}, {"id": 38086, "word": "CHURN", "definition": "v.搅拌, 搅动", "direction": "across", "start_row": 2, "start_col": 2, "length": 5, "clue_number": 2, "alternatives": [{"word": "CLEAN", "definition": "打扫"}, {"word": "CHAIN", "definition": "链条"}, {"word": "CABIN", "definition": "n.小屋；船舱"}, {"word": "CROWN", "definition": "n.花冠，王冠"}, {"word": "CLOWN", "definition": "n.小丑"}]}, {"id": 31646, "word": "MILL", "definition": "v.碾磨,搅拌", "direction": "down", "start_row": 2, "start_col": 8, "length": 4, "clue_number": 3, "alternatives": [{"word": "MILK", "definition": "牛奶"}, {"word": "WILL", "definition": "将要"}, {"word": "HILL", "definition": "小山"}, {"word": "FILM", "definition": "电影"}, {"word": "TILL", "definition": "直到"}]}, {"id": 39796, "word": "SKIM", "definition": "v. 撇去； 掠过， 擦过； 浏览， 略读", "direction": "across", "start_row": 3, "start_col": 6, "length": 4, "clue_number": 4, "alternatives": [{"word": "SWIM", "definition": "游泳"}, {"word": "SHIP", "definition": "船"}, {"word": "SKIN", "definition": "n. 皮； 兽皮， 毛皮； 外皮， 外壳"}, {"word": "SUIT", "definition": "n. 一套衣服； 套"}, {"word": "SAIL", "definition": "v.航行；驾驶；在…上航行; n. 帆； 航行"}]}, {"id": 40264, "word": "RESIGN", "definition": "v. 辞去， 辞职； 放弃； 顺从， 听从", "direction": "down", "start_row": 4, "start_col": 4, "length": 6, "clue_number": 5, "alternatives": [{"word": "DESIGN", "definition": "设计"}, {"word": "REGION", "definition": "n. 地区， 地带， 区域； 范围， 幅度"}, {"word": "BENIGN", "definition": "adj.良性的；和蔼的，亲切的；吉利的; n.(Benign)人名；(俄)贝尼根"}, {"word": "MEDIAN", "definition": "adj.中央的, [数学] 中线的, 中值的"}, {"word": "LEGION", "definition": "n.古罗马军团(约有3000至6000步兵,辅以数百名骑兵), <书>众多, 大批"}]}, {"id": 31627, "word": "WHEAT", "definition": "n.小麦", "direction": "across", "start_row": 5, "start_col": 2, "length": 5, "clue_number": 6, "alternatives": [{"word": "SWEET", "definition": "甜的"}, {"word": "SLEPT", "definition": "睡觉"}, {"word": "EVENT", "definition": "事件"}, {"word": "AGENT", "definition": "代理人"}, {"word": "CHEAT", "definition": "欺骗"}]}, {"id": 32770, "word": "FIRN", "definition": "n.粒雪, 积雪", "direction": "across", "start_row": 7, "start_col": 3, "length": 4, "clue_number": 7, "alternatives": [{"word": "LION", "definition": "n. 狮子"}, {"word": "SIGN", "definition": "v. 签； 签署; n.标志，符号；招牌；征兆，迹象"}, {"word": "KILN", "definition": "n.窑,炉"}, {"word": "LIEN", "definition": "n.留置权,抵押品所产生的利息"}, {"word": "MIEN", "definition": "n.风度"}]}, {"id": 36173, "word": "HANDER", "definition": "n.支持器,夹头", "direction": "across", "start_row": 9, "start_col": 2, "length": 6, "clue_number": 8, "alternatives": [{"word": "HUNGER", "definition": "v. 渴望， 渴望得到; n.饿，饥饿；食欲，胃口；渴望"}, {"word": "HUNGRY", "definition": "adj. 饥饿的， 感到饿的； 渴望得到的"}, {"word": "HONEST", "definition": "adj. 诚实的， 正直的； 坦诚的， 直率的"}, {"word": "HONOUR", "definition": "vt.尊敬，给予荣誉; n. 荣誉， 光荣"}, {"word": "HANDLE", "definition": "vt.处理; n. 柄， 把手"}]}], "prefilled": {"5-4": "E", "5-6": "T", "9-4": "N", "9-2": "H", "2-6": "N", "2-2": "C", "7-4": "I", "7-6": "N", "3-6": "S", "3-8": "I", "4-8": "L"}, "clue_numbers": [[null, null, null, null, null, null, 1, null, null, null], [null, null, null, null, null, null, null, null, null, null], [null, null, 2, null, null, null, null, null, 3, null], [null, null, null, null, null, null, 4, null, null, null], [null, null, null, null, 5, null, null, null, null, null], [null, null, 6, null, null, null, null, null, null, null], [null, null, null, null, null, null, null, null, null, null], [null, null, null, 7, null, null, null, null, null, null], [null, null, null, null, null, null, null, null, null, null], [null, null, 8, null, null, null, null, null, null, null]], "level": 95, "difficulty": "medium", "group": "toefl", "layout_type": "sparse", "group_name": "托福", "prefill_ratio": 0.25}