{"grid_size": 10, "cells": [[null, null, null, null, "", null, null, null, null, null], [null, null, "", "", "", "", "", null, null, null], [null, null, null, null, "", null, null, null, null, null], [null, null, "", "", "", "", "", "", null, null], ["", null, null, null, "", null, null, null, "", null], ["", null, "", "", "", "", "", null, "", null], ["", null, null, null, "", null, "", null, "", null], ["", null, null, null, "", "", "", "", "", ""], ["", null, null, null, null, null, "", null, "", null], ["", "", "", "", "", "", "", null, "", null]], "words": [{"id": 30182, "word": "INDICATE", "definition": "v. 标示， 表示， 表明； 象征； 暗示， 示意", "direction": "down", "start_row": 0, "start_col": 4, "length": 8, "clue_number": 1, "alternatives": [{"word": "INTIMATE", "definition": "adj.亲密的；个人的; n. 至交， 密友; vt. 暗示， 提示"}, {"word": "ENVISAGE", "definition": "vt. 想象， 设想"}, {"word": "INTIMACY", "definition": "n.亲密, 隐私"}]}, {"id": 25859, "word": "PANTS", "definition": "n.裤子", "direction": "across", "start_row": 1, "start_col": 2, "length": 5, "clue_number": 2, "alternatives": [{"word": "NINTH", "definition": "num.第九; n. 九分之一"}, {"word": "TENTH", "definition": "num.第十; n. 十分之一"}, {"word": "MONTH", "definition": "n. 月， 一个月的时间"}, {"word": "SANTA", "definition": "圣诞老人"}, {"word": "BANTU", "definition": "n.班图人, 班图语"}]}, {"id": 28274, "word": "CLIMAX", "definition": "n.顶点；小说等的高潮; v.达到高潮", "direction": "across", "start_row": 3, "start_col": 2, "length": 6, "clue_number": 3, "alternatives": [{"word": "ANIMAL", "definition": "动物"}, {"word": "PRIMAL", "definition": "adj.最初的"}, {"word": "GRIMLY", "definition": "adv.严格地,冷酷地"}, {"word": "PRIMER", "definition": "n.初级读本,原始物"}, {"word": "SKIMPY", "definition": "adj.不足的, 吝啬的"}]}, {"id": 25877, "word": "LAYOFF", "definition": "n.临时解雇，停工", "direction": "down", "start_row": 4, "start_col": 0, "length": 6, "clue_number": 4, "alternatives": [{"word": "PAYOFF", "definition": "n.发工资"}, {"word": "TARIFF", "definition": "n. 关税， 税率； 价目表， 收费表"}, {"word": "MASSIF", "definition": "n.山丘"}]}, {"id": 29693, "word": "BARREN", "definition": "adj. 贫瘠的， 荒芜的； 不结果实的， 不育的； 无益的， 无效果的", "direction": "down", "start_row": 4, "start_col": 8, "length": 6, "clue_number": 5, "alternatives": [{"word": "BORROW", "definition": "借"}, {"word": "BETRAY", "definition": "vt. 出卖， 背叛"}, {"word": "BARREL", "definition": "n.圆桶"}, {"word": "BURROW", "definition": "v.挖掘，钻进；翻寻; n. 地洞"}, {"word": "BARRED", "definition": "adj.有木栅的, 隔绝的, 被禁止的"}]}, {"id": 27559, "word": "CRAWL", "definition": "v.爬行;缓慢地行进，爬满; n.爬行；自由泳", "direction": "across", "start_row": 5, "start_col": 2, "length": 5, "clue_number": 6, "alternatives": [{"word": "SMALL", "definition": "小的"}, {"word": "EMAIL", "definition": "电子邮件"}, {"word": "SHALL", "definition": "表示征求意见"}, {"word": "PEARL", "definition": "n.珍珠"}, {"word": "SHAWL", "definition": "n.披肩，围巾"}]}, {"id": 25130, "word": "LOFTY", "definition": "adj.极高的，高尚的，高傲的", "direction": "down", "start_row": 5, "start_col": 6, "length": 5, "clue_number": 7, "alternatives": []}, {"id": 29646, "word": "EFFORT", "definition": "n. 努力， 艰难的尝试； 成就", "direction": "across", "start_row": 7, "start_col": 4, "length": 6, "clue_number": 8, "alternatives": [{"word": "BEFORE", "definition": "在⋯⋯之前"}, {"word": "AFFORD", "definition": "负担得起"}, {"word": "REFORM", "definition": "v. 改革， 革新; n.改革；改善"}, {"word": "INFORM", "definition": "v. 通知， 告诉"}, {"word": "BUFORD", "definition": "n.布福德（姓氏；男名）"}]}, {"id": 27242, "word": "FACULTY", "definition": "n.才能；(大学的)系科；学院全体教员", "direction": "across", "start_row": 9, "start_col": 0, "length": 7, "clue_number": 9, "alternatives": [{"word": "FACTORY", "definition": "工厂"}, {"word": "FINALLY", "definition": "最后"}, {"word": "FANTASY", "definition": "n. 幻想， 白日梦"}, {"word": "FREEWAY", "definition": "n. 高速公路"}, {"word": "FLUENCY", "definition": "n. 流利， 流畅"}]}], "prefilled": {"5-6": "L", "5-4": "A", "1-4": "N", "3-4": "I", "3-5": "M", "1-5": "T", "7-8": "R", "7-6": "F", "4-8": "B", "9-6": "Y", "9-0": "F", "5-0": "A"}, "clue_numbers": [[null, null, null, null, 1, null, null, null, null, null], [null, null, 2, null, null, null, null, null, null, null], [null, null, null, null, null, null, null, null, null, null], [null, null, 3, null, null, null, null, null, null, null], [4, null, null, null, null, null, null, null, 5, null], [null, null, 6, null, null, null, 7, null, null, null], [null, null, null, null, null, null, null, null, null, null], [null, null, null, null, 8, null, null, null, null, null], [null, null, null, null, null, null, null, null, null, null], [9, null, null, null, null, null, null, null, null, null]], "level": 690, "difficulty": "hard", "group": "ielts", "layout_type": "sparse", "group_name": "雅思", "prefill_ratio": 0.15}